feu/__init__.py
feu/__main__.py
feu/git.py
feu/imports.py
feu/package.py
feu/py.typed
feu/testing.py
feu/github/__init__.py
feu/github/repos.py
feu/github/sorting.py
feu/install/__init__.py
feu/install/installer.py
feu/install/registry.py
feu/install/utils.py
feu/install/pip/__init__.py
feu/install/pip/installer.py
feu/install/pip/resolver.py
feu/repo/__init__.py
feu/repo/github.py
feu/utils/__init__.py
feu/utils/command.py
feu/utils/http.py
feu/utils/installer.py
feu/utils/io.py
feu/utils/package.py
feu/utils/fallback/__init__.py
feu/utils/fallback/click.py
feu/utils/fallback/git.py
feu/utils/fallback/requests.py
feu/utils/fallback/urllib3.py
feu/version/__init__.py
feu/version/comparison.py
feu/version/filtering.py
feu/version/package.py
feu/version/pypi.py
feu/version/runtime.py
feu-0.6.1.dist-info/METADATA
feu-0.6.1.dist-info/WHEEL
feu-0.6.1.dist-info/licenses/LICENSE
feu-0.6.1.dist-info/RECORD
