Metadata-Version: 2.4
Name: feu
Version: 0.6.1
Dynamic: Maintainer
Dynamic: Maintainer-email
Summary: A lightweight Python library for managing packages and versions across different Python environments
Project-URL: homepage, https://github.com/durandtibo/feu
Project-URL: repository, https://github.com/durandtibo/feu
Project-URL: documentation, https://durandtibo.github.io/feu/
Author-email: Thibaut Durand <durand.tibo+gh@gmail.com>
License-Expression: BSD-3-Clause
License-File: LICENSE
Keywords: compatibility,dependency,install,package,package-manager,version,version-management
Classifier: Development Status :: 4 - Beta
Classifier: Intended Audience :: Developers
Classifier: Intended Audience :: Information Technology
Classifier: Intended Audience :: Science/Research
Classifier: License :: OSI Approved :: BSD License
Classifier: Operating System :: MacOS
Classifier: Operating System :: POSIX :: Linux
Classifier: Programming Language :: Python :: 3
Classifier: Programming Language :: Python :: 3.10
Classifier: Programming Language :: Python :: 3.11
Classifier: Programming Language :: Python :: 3.12
Classifier: Programming Language :: Python :: 3.13
Classifier: Programming Language :: Python :: 3.14
Classifier: Topic :: Scientific/Engineering
Classifier: Topic :: Software Development :: Libraries
Classifier: Topic :: Software Development :: Libraries :: Python Modules
Classifier: Topic :: System :: Installation/Setup
Classifier: Topic :: System :: Software Distribution
Classifier: Topic :: Utilities
Requires-Python: >=3.10
Requires-Dist: packaging<26.0,>=21.0
Requires-Dist: typing-extensions<5.0,>=4.10; python_version < '3.11'
Provides-Extra: all
Requires-Dist: click<9.0,>=8.1; extra == 'all'
Requires-Dist: gitpython<4.0,>=3.1.41; extra == 'all'
Requires-Dist: requests<3.0,>=2.30.0; extra == 'all'
Requires-Dist: urllib3<3.0,>=2.0; extra == 'all'
Provides-Extra: cli
Requires-Dist: click<9.0,>=8.1; extra == 'cli'
Provides-Extra: git
Requires-Dist: gitpython<4.0,>=3.1.41; extra == 'git'
Provides-Extra: requests
Requires-Dist: requests<3.0,>=2.30.0; extra == 'requests'
Requires-Dist: urllib3<3.0,>=2.0; extra == 'requests'
